algs4/acyclic_sp.py
algs4/bag.py
algs4/bellman_ford_sp.py
algs4/binary_search.py
algs4/binary_search_st.py
algs4/binarydump.py
algs4/binarystdin.py
algs4/binarystdout.py
algs4/breadth_first_paths.py
algs4/bst.py
algs4/cc.py
algs4/cycle.py
algs4/degrees_of_separation.py
algs4/depth_first_order.py
algs4/depth_first_paths.py
algs4/depth_first_search.py
algs4/digraph.py
algs4/dijkstra_sp.py
algs4/directed_cycle.py
algs4/directed_dfs.py
algs4/directed_edge.py
algs4/edge.py
algs4/edge_weighted_digraph.py
algs4/edge_weighted_directed_cycle.py
algs4/edge_weighted_graph.py
algs4/frequency_counter.py
algs4/graph.py
algs4/heap.py
algs4/huffman.py
algs4/index_min_pq.py
algs4/insertion.py
algs4/kmp.py
algs4/kosaraju_scc.py
algs4/kruskal_mst.py
algs4/lazy_prim_mst.py
algs4/linear_probing_hash_st.py
algs4/lsd.py
algs4/lzw.py
algs4/max_pq.py
algs4/merge.py
algs4/min_pq.py
algs4/msd.py
algs4/multiway.py
algs4/nfa.py
algs4/prim_mst.py
algs4/queue.py
algs4/quick.py
algs4/quick3_string.py
algs4/quick_3way.py
algs4/red_black_bst.py
algs4/selection.py
algs4/separate_chaining_hash_st.py
algs4/sequential_search_st.py
algs4/shell.py
algs4/st.py
algs4/stack.py
algs4/stopwatch.py
algs4/symbol_digraph.py
algs4/symbol_graph.py
algs4/top_m.py
algs4/topological.py
algs4/transaction.py
algs4/trie_st.py
algs4/tst.py
algs4/uf.py
algs4/utils/linklist.py
algs4/utils/st.py
algs4-1.0.3.dist-info/LICENSE
algs4-1.0.3.dist-info/METADATA
algs4-1.0.3.dist-info/WHEEL
algs4-1.0.3.dist-info/top_level.txt
algs4-1.0.3.dist-info/RECORD
