Metadata-Version: 2.1
Name: algs4
Version: 1.0.3
Summary: A Python implementation library for book algs4
Home-page: https://github.com/shellfly/algs4-py
Author: shellfly
Author-email: shell0fly@gmail.com
License: UNKNOWN
Keywords: algs4 algorithm
Platform: UNKNOWN
Classifier: Development Status :: 4 - Beta
Classifier: Intended Audience :: Developers
Classifier: Topic :: Software Development :: Build Tools
Classifier: License :: OSI Approved :: MIT License
Classifier: Programming Language :: Python :: 3
License-File: LICENSE
